SPCE/__init__.py
SPCE/claim.py
SPCE/debug.py
SPCE/dummy.py
SPCE/pipeline.py
SPCE/preprocess.py
SPCE/run.py
SPCE/discourse/__init__.py
SPCE/discourse/utils.py
SPCE/discourse/dataset_readers/__init__.py
SPCE/discourse/dataset_readers/claim_dataset.py
SPCE/discourse/dataset_readers/crf_pubmed_rct.py
SPCE/discourse/dataset_readers/pubmed_rct.py
SPCE/discourse/models/__init__.py
SPCE/discourse/models/alternate_model.py
SPCE/discourse/models/discourse_bnn_model.py
SPCE/discourse/models/discourse_crf_model.py
SPCE/discourse/models/discourse_model.py
SPCE/discourse/predictors/__init__.py
SPCE/discourse/predictors/discourse_bnn_predictor.py
SPCE/discourse/predictors/discourse_crf_predictor.py
SPCE/discourse/predictors/discourse_predictor.py
Scientific_Publication_Claim_Extraction-1.0.0.dist-info/LICENSE
Scientific_Publication_Claim_Extraction-1.0.0.dist-info/METADATA
Scientific_Publication_Claim_Extraction-1.0.0.dist-info/WHEEL
Scientific_Publication_Claim_Extraction-1.0.0.dist-info/top_level.txt
Scientific_Publication_Claim_Extraction-1.0.0.dist-info/RECORD
