Metadata-Version: 2.1
Name: Scientific-Publication-Claim-Extraction
Version: 1.0.0
Summary: This package could be used to extract claims from scientific publication
Home-page: https://github.com/juvena-therapeutics/scientific-claim
Author: Xi Chen
Author-email: bchen@juvenatherapeutics.com
License: UNKNOWN
Platform: UNKNOWN
Classifier: Programming Language :: Python :: 3
Classifier: License :: OSI Approved :: MIT License
Classifier: Operating System :: OS Independent
Requires-Python: >=3.6
